plone.z3cform-2.0.5-py3.13-nspkg.pth
plone/z3cform/__init__.py
plone/z3cform/configure.zcml
plone/z3cform/converter.py
plone/z3cform/inputs.txt
plone/z3cform/interfaces.py
plone/z3cform/layout.py
plone/z3cform/layout.rst
plone/z3cform/overrides.zcml
plone/z3cform/patch.py
plone/z3cform/subform.py
plone/z3cform/templates.py
plone/z3cform/templates.zcml
plone/z3cform/testing.zcml
plone/z3cform/tests.py
plone/z3cform/traversal.py
plone/z3cform/traversal.txt
plone/z3cform/widget.py
plone/z3cform/z2.py
plone/z3cform/crud/README.txt
plone/z3cform/crud/__init__.py
plone/z3cform/crud/crud-add.pt
plone/z3cform/crud/crud-master.pt
plone/z3cform/crud/crud-row.pt
plone/z3cform/crud/crud-table.pt
plone/z3cform/crud/crud.py
plone/z3cform/fieldsets/README.rst
plone/z3cform/fieldsets/__init__.py
plone/z3cform/fieldsets/extensible.py
plone/z3cform/fieldsets/group.py
plone/z3cform/fieldsets/interfaces.py
plone/z3cform/fieldsets/utils.py
plone/z3cform/locales/plone.z3cform.pot
plone/z3cform/locales/update.sh
plone/z3cform/locales/de/LC_MESSAGES/plone.z3cform.mo
plone/z3cform/locales/de/LC_MESSAGES/plone.z3cform.po
plone/z3cform/locales/en/LC_MESSAGES/plone.z3cform.mo
plone/z3cform/locales/en/LC_MESSAGES/plone.z3cform.po
plone/z3cform/locales/fr/LC_MESSAGES/plone.z3cform.mo
plone/z3cform/locales/fr/LC_MESSAGES/plone.z3cform.po
plone/z3cform/locales/it/LC_MESSAGES/plone.z3cform.mo
plone/z3cform/locales/it/LC_MESSAGES/plone.z3cform.po
plone/z3cform/locales/nl/LC_MESSAGES/plone.z3cform.mo
plone/z3cform/locales/nl/LC_MESSAGES/plone.z3cform.po
plone/z3cform/locales/no/LC_MESSAGES/plone.z3cform.mo
plone/z3cform/locales/no/LC_MESSAGES/plone.z3cform.po
plone/z3cform/locales/pt_BR/LC_MESSAGES/plone.z3cform.mo
plone/z3cform/locales/pt_BR/LC_MESSAGES/plone.z3cform.po
plone/z3cform/locales/uk/LC_MESSAGES/plone.z3cform.mo
plone/z3cform/locales/uk/LC_MESSAGES/plone.z3cform.po
plone/z3cform/locales/zh_CN/LC_MESSAGES/plone.z3cform.mo
plone/z3cform/locales/zh_CN/LC_MESSAGES/plone.z3cform.po
plone_z3cform-2.0.5.dist-info/licenses/LICENSE.rst
plone_z3cform-2.0.5.dist-info/METADATA
plone_z3cform-2.0.5.dist-info/WHEEL
plone_z3cform-2.0.5.dist-info/namespace_packages.txt
plone_z3cform-2.0.5.dist-info/top_level.txt
plone_z3cform-2.0.5.dist-info/RECORD
