Metadata-Version: 2.4
Name: plone.z3cform
Version: 2.0.5
Summary: plone.z3cform is a library that allows use of z3c.form with Zope and the CMF.
Home-page: https://github.com/plone/plone.z3cform
Author: Plone Foundation
Author-email: releasemanager@plone.org
License: GPL version 2
Keywords: Plone CMF Python Zope CMS Webapplication
Classifier: Development Status :: 5 - Production/Stable
Classifier: Environment :: Web Environment
Classifier: Framework :: Plone
Classifier: Framework :: Plone :: 6.0
Classifier: Framework :: Plone :: Core
Classifier: Framework :: Zope :: 5
Classifier: License :: OSI Approved :: GNU General Public License v2 (GPLv2)
Classifier: Operating System :: OS Independent
Classifier: Programming Language :: Python
Classifier: Programming Language :: Python :: 3.8
Classifier: Programming Language :: Python :: 3.9
Classifier: Programming Language :: Python :: 3.10
Classifier: Programming Language :: Python :: 3.11
Requires-Python: >=3.8
License-File: LICENSE.rst
Requires-Dist: setuptools
Requires-Dist: plone.batching
Requires-Dist: z3c.form>=4.0
Requires-Dist: zope.browserpage
Requires-Dist: zope.pagetemplate
Requires-Dist: Zope
Provides-Extra: test
Requires-Dist: persistent; extra == "test"
Requires-Dist: plone.testing; extra == "test"
Requires-Dist: zope.annotation; extra == "test"
Dynamic: author
Dynamic: author-email
Dynamic: classifier
Dynamic: description
Dynamic: home-page
Dynamic: keywords
Dynamic: license
Dynamic: license-file
Dynamic: provides-extra
Dynamic: requires-dist
Dynamic: requires-python
Dynamic: summary
